bootstrap_colors/__init__.py
bootstrap_colors/views.py
bootstrap_colors/templates/bootstrap_colors.css
django_bootstrap_colors-5.4.1.dist-info/licenses/LICENSE
django_bootstrap_colors-5.4.1.dist-info/METADATA
django_bootstrap_colors-5.4.1.dist-info/WHEEL
django_bootstrap_colors-5.4.1.dist-info/top_level.txt
django_bootstrap_colors-5.4.1.dist-info/RECORD
