Metadata-Version: 2.4
Name: django-bootstrap-colors
Version: 5.4.1
Summary: override the primary color and its variants in bootstrap
Author: Max-Planck-Gesellschaft
License-Expression: MIT
Project-URL: Homepage, https://git.mpib-berlin.mpg.de/castellum/django-bootstrap-colors
License-File: LICENSE
Dynamic: license-file
